unsloth-stubs/__init__.pyi
unsloth-stubs/_auto_install.pyi
unsloth-stubs/chat_templates.pyi
unsloth-stubs/dataprep/__init__.pyi
unsloth-stubs/dataprep/synthetic.pyi
unsloth-stubs/dataprep/synthetic_configs.pyi
unsloth-stubs/import_fixes.pyi
unsloth-stubs/kernels/__init__.pyi
unsloth-stubs/kernels/cross_entropy_loss.pyi
unsloth-stubs/kernels/fast_lora.pyi
unsloth-stubs/kernels/flex_attention.pyi
unsloth-stubs/kernels/geglu.pyi
unsloth-stubs/kernels/layernorm.pyi
unsloth-stubs/kernels/moe/__init__.pyi
unsloth-stubs/kernels/moe/grouped_gemm/__init__.pyi
unsloth-stubs/kernels/moe/grouped_gemm/interface.pyi
unsloth-stubs/kernels/moe/grouped_gemm/kernels/__init__.pyi
unsloth-stubs/kernels/moe/grouped_gemm/kernels/autotuning.pyi
unsloth-stubs/kernels/moe/grouped_gemm/kernels/backward.pyi
unsloth-stubs/kernels/moe/grouped_gemm/kernels/forward.pyi
unsloth-stubs/kernels/moe/grouped_gemm/kernels/tuning.pyi
unsloth-stubs/kernels/moe/grouped_gemm/reference/__init__.pyi
unsloth-stubs/kernels/moe/grouped_gemm/reference/moe_block.pyi
unsloth-stubs/kernels/moe/grouped_gemm/reference/moe_ops.pyi
unsloth-stubs/kernels/rms_layernorm.pyi
unsloth-stubs/kernels/rope_embedding.pyi
unsloth-stubs/kernels/swiglu.pyi
unsloth-stubs/kernels/utils.pyi
unsloth-stubs/models/__init__.pyi
unsloth-stubs/models/_utils.pyi
unsloth-stubs/models/cohere.pyi
unsloth-stubs/models/dpo.pyi
unsloth-stubs/models/falcon_h1.pyi
unsloth-stubs/models/gemma.pyi
unsloth-stubs/models/gemma2.pyi
unsloth-stubs/models/granite.pyi
unsloth-stubs/models/llama.pyi
unsloth-stubs/models/llama4.pyi
unsloth-stubs/models/loader.pyi
unsloth-stubs/models/loader_utils.pyi
unsloth-stubs/models/mapper.pyi
unsloth-stubs/models/mistral.pyi
unsloth-stubs/models/qwen2.pyi
unsloth-stubs/models/qwen3.pyi
unsloth-stubs/models/qwen3_moe.pyi
unsloth-stubs/models/rl.pyi
unsloth-stubs/models/rl_replacements.pyi
unsloth-stubs/models/vision.pyi
unsloth-stubs/registry/__init__.pyi
unsloth-stubs/registry/_deepseek.pyi
unsloth_stubs-0.0.0.dev0.dist-info/WHEEL
unsloth_stubs-0.0.0.dev0.dist-info/METADATA
unsloth_stubs-0.0.0.dev0.dist-info/RECORD
