Metadata-Version: 2.3
Name: unsloth-stubs
Version: 0.0.0.dev0
Summary: Type stubs for the Unsloth library, providing enhanced type checking and autocompletion for Python developers.
Author: D. Danchev
Author-email: D. Danchev <12420863+danchev@users.noreply.github.com>
License: MIT
Classifier: Development Status :: 2 - Pre-Alpha
Classifier: Intended Audience :: Developers
Classifier: Operating System :: OS Independent
Classifier: License :: OSI Approved :: MIT License
Classifier: Programming Language :: Python :: 3
Classifier: Programming Language :: Python :: 3.11
Classifier: Programming Language :: Python :: 3.12
Classifier: Programming Language :: Python :: 3.13
Classifier: Typing :: Stubs Only
Requires-Python: >=3.11
Project-URL: Homepage, https://github.com/danchev/unsloth-stubs
Project-URL: Issues, https://github.com/danchev/unsloth-stubs/issues
